weekfivepackage/__init__.py
weekfivepackage/src/__init__.py
weekfivepackage/src/week2_to_4.py
weekfivepackage-1.0.dist-info/LICENSE
weekfivepackage-1.0.dist-info/METADATA
weekfivepackage-1.0.dist-info/WHEEL
weekfivepackage-1.0.dist-info/top_level.txt
weekfivepackage-1.0.dist-info/RECORD
