Metadata-Version: 2.1
Name: weekfivepackage
Version: 1.0
Summary: This is a weekfivepackage.
Author: Ajit Shrestha
Author-email: ajitstha16@gmail.com
License-File: LICENSE
